{"cameraMode":{"drawMode":0,"name":"Shaded","section":"Shading Mode"},"sceneLighting":false,"audioPlay":false,"sceneViewState":{"showFog":true,"showMaterialUpdate":false,"showSkybox":false,"showFlares":true,"showImageEffects":true,"showParticleSystems":true,"showVisualEffectGraphs":true,"m_FxEnabled":true},"in2DMode":false,"pivot":{"x":20.555437088012697,"y":8.579410552978516,"z":23.453500747680665},"rotation":{"x":-0.22825060784816743,"y":0.7179965376853943,"z":-0.27420860528945925,"w":-0.5976760387420654},"size":29.08660316467285,"orthographic":false}